{
    "MaxEpsilonIneqDelay": {
        "event_rightCont_timeAvg": {
            "A0D0": {
                "0": 50
            }
        },
        "event_leftCont_timeAvg": {
            "A0D0": {
                "0": 0
            }
        },
        "event_linearInterp_timeAvg": {
            "A0D0": {
                "0": 50
            }
        }
    },
    "MaxEpsilonIneqSuccessProb": {
        "probability_rightCont_timeAvg": {
            "A0D0": {
                "0": 50
            }
        },
        "probability_leftCont_timeAvg": {
            "A0D0": {
                "0": 50
            }
        },
        "probability_linearInterp_timeAvg": {
            "A0D0": {
                "0": 50
            }
        }
    },
    "MaxEpsilonIneqNonMarkingProb": {
        "event_rightCont_timeAvg": {
            "A0D0": {
                "0": 42
            }
        },
        "event_leftCont_timeAvg": {
            "A0D0": {
                "0": 39
            }
        },
        "event_linearInterp_timeAvg": {
            "A0D0": {
                "0": 38
            }
        }
    },
    "MaxEpsilonIneqLastNonMarkingProb": {
        "event_rightCont_timeAvg": {
            "A0D0": {
                "0": 42
            }
        },
        "event_leftCont_timeAvg": {
            "A0D0": {
                "0": 39
            }
        },
        "event_linearInterp_timeAvg": {
            "A0D0": {
                "0": 39
            }
        }
    },
    "EndToEndDelayMean": {
        "event_rightCont_timeAvg": {
            "A0D0": {
                "0": [
                    17026.076359437713,
                    16810.059086471225,
                    16764.922282772524,
                    16986.619958602932,
                    16917.654183290553,
                    16967.48161154395,
                    16943.21043936282,
                    17104.3675937231,
                    16974.323838812732,
                    16984.1370038117,
                    16871.633429441372,
                    16922.929779773203,
                    17006.180195439974,
                    16912.450512689622,
                    16833.258449121182,
                    16956.248246072937,
                    16949.052092359325,
                    16939.854777975852,
                    16862.318297297228,
                    16948.786707020306,
                    17000.756259147256,
                    17102.980899160815,
                    16990.92683046211,
                    16892.996410085336,
                    16913.033305438224,
                    16937.689574976088,
                    17094.861473262237,
                    16886.72024009613,
                    16886.17129418492,
                    16969.53104000825,
                    16896.336689013875,
                    16978.984267675016,
                    16671.793140390204,
                    16956.068287294875,
                    16779.16899766833,
                    16982.418345287417,
                    16652.109704268878,
                    16946.99795738024,
                    17147.538280690394,
                    16888.593964789412,
                    17157.792941657553,
                    16990.488326234878,
                    17131.954821953655,
                    16618.161260118763,
                    17204.07444537691,
                    16935.96297156718,
                    16895.56888541019,
                    16947.473230550877,
                    17030.430153047037,
                    17037.676981426015
                ]
            }
        },
        "event_leftCont_timeAvg": {
            "A0D0": {
                "0": [
                    11092.359492916745,
                    11036.911911608677,
                    11050.58864553076,
                    10998.292275916168,
                    11041.885342124311,
                    11024.998689682896,
                    11058.324303473035,
                    10980.320224085106,
                    11021.258898431981,
                    11020.13725247522,
                    11038.019926538156,
                    11065.796732514893,
                    11029.686196773551,
                    11063.152223535133,
                    11020.37880661621,
                    11055.631283600496,
                    10976.928839279097,
                    10974.964113512795,
                    11021.949606160664,
                    11025.538327689646,
                    11037.378890735665,
                    10982.732709500648,
                    11025.134426341945,
                    11046.41724901666,
                    11051.871724643639,
                    10961.649140772937,
                    11046.524648473523,
                    11088.659063847266,
                    11028.820672157586,
                    11051.606019638326,
                    11087.55866569427,
                    11011.688882817378,
                    11031.585316400264,
                    11040.07841868617,
                    11033.828818212865,
                    10984.764573551194,
                    11075.807243756579,
                    11057.504538653322,
                    11055.880413224944,
                    11028.953868555654,
                    11069.417611190207,
                    11032.870715439352,
                    11015.656727811029,
                    11006.990091700764,
                    10993.986531958126,
                    11046.801582708147,
                    11041.196611913178,
                    11049.906458035852,
                    11017.386993041815,
                    11022.514603256363
                ]
            }
        },
        "event_linearInterp_timeAvg": {
            "A0D0": {
                "0": [
                    13479.99908024011,
                    13368.914883054551,
                    13364.60838658891,
                    13442.773646848698,
                    13428.112205254438,
                    13436.94327984036,
                    13430.360632951906,
                    13496.159489474912,
                    13436.681111140642,
                    13443.582836969807,
                    13405.034166073086,
                    13439.104849991507,
                    13456.464966490046,
                    13424.797504804408,
                    13386.831304571353,
                    13438.765790087788,
                    13436.138577002004,
                    13421.590675344009,
                    13382.838734947265,
                    13429.344720395435,
                    13453.630052068946,
                    13490.257803876504,
                    13469.56660338247,
                    13421.043351673501,
                    13429.273646489231,
                    13419.632403030027,
                    13501.179659126428,
                    13416.645173616434,
                    13413.763987159587,
                    13461.113703073106,
                    13418.129794835548,
                    13457.409577931117,
                    13322.605681853767,
                    13422.051514782279,
                    13370.807640022927,
                    13445.74491563198,
                    13308.48387554158,
                    13448.311607892203,
                    13535.70013859229,
                    13410.578889588785,
                    13537.314240745398,
                    13457.951350675514,
                    13511.181431504734,
                    13285.795687969114,
                    13535.226156723089,
                    13436.075836480795,
                    13417.55403564189,
                    13437.870065766736,
                    13478.716305085249,
                    13471.056856148003
                ]
            }
        }
    },
    "EndToEndSuccessProb": {
        "probability_rightCont_timeAvg": {
            "A0D0": {
                "0": [
                    1.0,
                    1.0,
                    1.0,
                    1.0,
                    1.0,
                    1.0,
                    1.0,
                    1.0,
                    1.0,
                    1.0,
                    1.0,
                    1.0,
                    1.0,
                    1.0,
                    1.0,
                    1.0,
                    1.0,
                    1.0,
                    1.0,
                    1.0,
                    1.0,
                    1.0,
                    1.0,
                    1.0,
                    1.0,
                    1.0,
                    1.0,
                    1.0,
                    1.0,
                    1.0,
                    1.0,
                    1.0,
                    1.0,
                    1.0,
                    1.0,
                    1.0,
                    1.0,
                    1.0,
                    1.0,
                    1.0,
                    1.0,
                    1.0,
                    1.0,
                    1.0,
                    1.0,
                    1.0,
                    1.0,
                    1.0,
                    1.0,
                    1.0
                ]
            }
        },
        "probability_leftCont_timeAvg": {
            "A0D0": {
                "0": [
                    1.0,
                    1.0,
                    1.0,
                    1.0,
                    1.0,
                    1.0,
                    1.0,
                    1.0,
                    1.0,
                    1.0,
                    1.0,
                    1.0,
                    1.0,
                    1.0,
                    1.0,
                    1.0,
                    1.0,
                    1.0,
                    1.0,
                    1.0,
                    1.0,
                    1.0,
                    1.0,
                    1.0,
                    1.0,
                    1.0,
                    1.0,
                    1.0,
                    1.0,
                    1.0,
                    1.0,
                    1.0,
                    1.0,
                    1.0,
                    1.0,
                    1.0,
                    1.0,
                    1.0,
                    1.0,
                    1.0,
                    1.0,
                    1.0,
                    1.0,
                    1.0,
                    1.0,
                    1.0,
                    1.0,
                    1.0,
                    1.0,
                    1.0
                ]
            }
        },
        "probability_linearInterp_timeAvg": {
            "A0D0": {
                "0": [
                    1.0,
                    1.0,
                    1.0,
                    1.0,
                    1.0,
                    1.0,
                    1.0,
                    1.0,
                    1.0,
                    1.0,
                    1.0,
                    1.0,
                    1.0,
                    1.0,
                    1.0,
                    1.0,
                    1.0,
                    1.0,
                    1.0,
                    1.0,
                    1.0,
                    1.0,
                    1.0,
                    1.0,
                    1.0,
                    1.0,
                    1.0,
                    1.0,
                    1.0,
                    1.0,
                    1.0,
                    1.0,
                    1.0,
                    1.0,
                    1.0,
                    1.0,
                    1.0,
                    1.0,
                    1.0,
                    1.0,
                    1.0,
                    1.0,
                    1.0,
                    1.0,
                    1.0,
                    1.0,
                    1.0,
                    1.0,
                    1.0,
                    1.0
                ]
            }
        }
    },
    "EndToEndNonMarkingProb": {
        "event_rightCont_timeAvg": {
            "A0D0": {
                "0": [
                    1.0,
                    0.999999189937878,
                    1.0,
                    0.9999962117046342,
                    0.9999993819676819,
                    1.0,
                    0.9999625649088347,
                    0.9999979878040041,
                    0.99996626938075,
                    1.0,
                    0.9999990319620026,
                    0.999999131977072,
                    0.9999590225540974,
                    0.9999957717515904,
                    0.999963268340684,
                    0.9999635822960885,
                    0.999966528560274,
                    1.0,
                    0.999961937947618,
                    0.9999996399584923,
                    1.0,
                    1.0,
                    0.9999992079266065,
                    1.0,
                    0.9999609572331953,
                    1.0,
                    0.9999663279159545,
                    0.9999986799465115,
                    1.0,
                    1.0,
                    1.0,
                    0.9999980978884069,
                    0.9999651161605451,
                    0.9999875192026019,
                    0.9999985738427634,
                    0.9999958255032516,
                    0.9999988319752683,
                    0.9999668558944875,
                    1.0,
                    1.0,
                    1.0,
                    0.9999981779701698,
                    1.0,
                    1.0,
                    0.9999987499036651,
                    1.0,
                    0.9999797895947192,
                    1.0,
                    1.0,
                    0.9999644932759242
                ]
            }
        },
        "event_leftCont_timeAvg": {
            "A0D0": {
                "0": [
                    1.0,
                    0.9999992559429397,
                    1.0,
                    0.9999945815775364,
                    0.9999988579402794,
                    1.0,
                    0.9999144429352109,
                    0.9999991119134968,
                    0.9999590968237866,
                    1.0,
                    0.9999976539079112,
                    0.9999991079764381,
                    0.9999940732123299,
                    0.9999557914027449,
                    0.9998820326709439,
                    0.999961230186038,
                    0.9999595218402214,
                    1.0,
                    0.9999474811680795,
                    0.999998599838581,
                    1.0,
                    1.0,
                    0.9999992379293865,
                    1.0,
                    0.9999615072721744,
                    1.0,
                    0.9999571418930262,
                    0.9999963738530685,
                    1.0,
                    1.0,
                    1.0,
                    0.9999990539444968,
                    0.9999532608557028,
                    0.9999601374531819,
                    0.9999996659631718,
                    0.9999205905505931,
                    0.9999967999322418,
                    0.99999530570179,
                    1.0,
                    1.0,
                    1.0,
                    0.99996145736898,
                    1.0,
                    1.0,
                    0.9999996959765713,
                    1.0,
                    0.9999968616264959,
                    1.0,
                    1.0,
                    0.9999573367268737
                ]
            }
        },
        "event_linearInterp_timeAvg": {
            "A0D0": {
                "0": [
                    1.0,
                    0.9999992229404089,
                    1.0,
                    0.9999953966410853,
                    0.9999991199539806,
                    1.0,
                    0.9999385039220229,
                    0.9999985498587505,
                    0.9999626831022682,
                    1.0,
                    0.9999983429349569,
                    0.9999991199767551,
                    0.9999765478832137,
                    0.9999757815771677,
                    0.999922650505814,
                    0.9999624062410633,
                    0.9999630252002477,
                    1.0,
                    0.9999547095578488,
                    0.9999991198985366,
                    1.0,
                    1.0,
                    0.9999992229279965,
                    1.0,
                    0.9999612322526849,
                    1.0,
                    0.9999617349044904,
                    0.9999975268997899,
                    1.0,
                    1.0,
                    1.0,
                    0.9999985759164519,
                    0.9999591885081239,
                    0.9999738283278918,
                    0.9999991199029675,
                    0.9999582080269224,
                    0.999997815953755,
                    0.9999810807981387,
                    1.0,
                    1.0,
                    1.0,
                    0.9999798176695749,
                    1.0,
                    1.0,
                    0.9999992229401182,
                    1.0,
                    0.9999883256106076,
                    1.0,
                    1.0,
                    0.9999609150013989
                ]
            }
        }
    },
    "DropRate": [
        0.0,
        0.0,
        0.0,
        0.0,
        0.0,
        0.0,
        0.0,
        0.0,
        0.0,
        0.0,
        0.0,
        0.0,
        0.0,
        0.0,
        0.0,
        0.0,
        0.0,
        0.0,
        0.0,
        0.0,
        0.0,
        0.0,
        0.0,
        0.0,
        0.0,
        0.0,
        0.0,
        0.0,
        0.0,
        0.0,
        0.0,
        0.0,
        0.0,
        0.0,
        0.0,
        0.0,
        0.0,
        0.0,
        0.0,
        0.0,
        0.0,
        0.0,
        0.0,
        0.0,
        0.0,
        0.0,
        0.0,
        0.0,
        0.0,
        0.0
    ],
    "maxEpsilonDelay": {
        "A0D0": {
            "0": [
                0.2510346040956058,
                0.26846003067190266,
                0.2602270223965729,
                0.25693325454747634,
                0.26479983730116213,
                0.2526913531495984,
                0.2619443297265776,
                0.256838205635432,
                0.2568938719208019,
                0.25192698729933455,
                0.2646610763339642,
                0.2619362633805518,
                0.2587289545292906,
                0.26352930971293687,
                0.2551515477294502,
                0.2601105606608807,
                0.25538747450003485,
                0.25555604420217326,
                0.2601068937605787,
                0.25980562728457546,
                0.25634062634149624,
                0.25180776502370356,
                0.25859387749952784,
                0.2661454139476455,
                0.26061199794181794,
                0.25663895545455323,
                0.25416459064472785,
                0.25999937313597155,
                0.2573422517331227,
                0.25423946320355834,
                0.26122529452058635,
                0.25008171375291405,
                0.26207643802758496,
                0.2606928048868758,
                0.2619723890188745,
                0.2508683227384973,
                0.27357739088256106,
                0.2556782570970592,
                0.2485826861527085,
                0.2532489621811452,
                0.24672000348939327,
                0.2506825964445954,
                0.25066105633926633,
                0.26613269567608305,
                0.25450906326610534,
                0.2607997299829271,
                0.2555067937036692,
                0.25063108193772526,
                0.25371098208754295,
                0.2508420359340163
            ]
        }
    },
    "maxEpsilonSuccessProb": {
        "A0D0": {
            "0": [
                0.0,
                0.0,
                0.0,
                0.0,
                0.0,
                0.0,
                0.0,
                0.0,
                0.0,
                0.0,
                0.0,
                0.0,
                0.0,
                0.0,
                0.0,
                0.0,
                0.0,
                0.0,
                0.0,
                0.0,
                0.0,
                0.0,
                0.0,
                0.0,
                0.0,
                0.0,
                0.0,
                0.0,
                0.0,
                0.0,
                0.0,
                0.0,
                0.0,
                0.0,
                0.0,
                0.0,
                0.0,
                0.0,
                0.0,
                0.0,
                0.0,
                0.0,
                0.0,
                0.0,
                0.0,
                0.0,
                0.0,
                0.0,
                0.0,
                0.0
            ]
        }
    },
    "maxEpsilonNonMarkingProb": {
        "A0D0": {
            "0": [
                0.0,
                2.7990946569733663e-06,
                1.3053904939708261e-06,
                2.2894585045607486e-06,
                1.2779868284740203e-06,
                0.0,
                6.23370674212076e-05,
                9.487324103574223e-07,
                6.396760721270489e-05,
                0.0,
                4.759066802884071e-06,
                3.2144849072768268e-06,
                7.754398559584707e-05,
                3.5321275125488328e-06,
                6.579625227976394e-05,
                7.061818408350184e-05,
                6.420051763048828e-05,
                3.48904006619577e-07,
                7.140273017810283e-05,
                8.977835019718938e-07,
                0.0,
                3.0969331424657295e-07,
                0.0,
                0.0,
                6.092895779158169e-05,
                0.0,
                0.0003231946170520794,
                2.1678478412345824e-06,
                1.1917635927094494e-06,
                0.0,
                0.0,
                1.399522107128348e-06,
                6.340513862312935e-05,
                1.0314178972925525e-05,
                1.4976051140802583e-06,
                6.6491112175270924e-06,
                0.0,
                6.174392234449488e-05,
                0.0,
                0.0,
                3.645885151426498e-07,
                3.198772370307523e-06,
                0.0,
                0.0,
                5.802047118175224e-07,
                0.0,
                3.466868598979822e-05,
                5.684405820316485e-07,
                0.0,
                5.903972952795211e-05
            ]
        }
    },
    "maxEpsilonLastNonMarkingProb": {
        "A0D0": {
            "0": [
                0.0,
                2.7990946569733663e-06,
                1.395552600218508e-06,
                1.7131735726350073e-06,
                7.801207940838495e-07,
                0.0,
                5.64134582850162e-05,
                0.0003269285965590549,
                6.084312459023522e-05,
                0.0,
                0.0003226043163109183,
                0.0,
                5.337005288015284e-05,
                1.1682286334240289e-05,
                0.00032034212901319205,
                0.00032407453233347953,
                1.1302521514906516e-05,
                0.0,
                0.000121444228515597,
                0.0,
                0.0,
                0.0,
                4.312399572548031e-08,
                0.0,
                0.0003208915838570226,
                0.0,
                0.00032494995670609943,
                8.471463263766132e-06,
                0.0,
                0.0,
                0.0,
                4.5474667906386654e-07,
                6.135475294946513e-05,
                0.0004634918111585655,
                2.5090766306634648e-06,
                0.00032333451210839295,
                0.0,
                0.0003462502938712716,
                0.0,
                0.0,
                0.00032986041542790005,
                0.0,
                0.0,
                0.0,
                0.0003265578140619794,
                0.0,
                3.0505150478958853e-05,
                5.684405820316485e-07,
                0.0,
                0.0003321513928098218
            ]
        }
    },
    "workLoad": {
        "A0D0": {
            "0": [
                0,
                0,
                0,
                0,
                0,
                0,
                0,
                0,
                0,
                0,
                0,
                0,
                0,
                0,
                0,
                0,
                0,
                0,
                0,
                0,
                0,
                0,
                0,
                0,
                0,
                0,
                0,
                0,
                0,
                0,
                0,
                0,
                0,
                0,
                0,
                0,
                0,
                0,
                0,
                0,
                0,
                0,
                0,
                0,
                0,
                0,
                0,
                0,
                0,
                0
            ]
        }
    },
    "AverageWorkLoad": 0.0,
    "experiments": 50,
    "SD0Delaystd": [
        8418.133978626429,
        8431.660638007463,
        8468.854540136916,
        8472.117844164175,
        8660.625174796814,
        8462.732031575777,
        8492.026038003143,
        8491.090062176912,
        8436.746568512572,
        8515.303643086749,
        8463.059976170765,
        8572.844390086158,
        8584.506589644609,
        8477.653080569578,
        8446.911796680022,
        8479.376214787388,
        8573.454240710455,
        8375.651844878072,
        8427.460463607278,
        8455.341777765685,
        8474.26956528933,
        8515.194157701986,
        8593.635863797019,
        8499.427159612489,
        8567.908022635855,
        8517.214601078504,
        8558.835616411052,
        8324.985000484678,
        8510.219693709361,
        8362.62748086087,
        8521.772295295918,
        8495.937911756755,
        8396.0047270474,
        8505.1949945276,
        8414.810745958557,
        8523.949413017757,
        8562.032891853667,
        8434.241146427215,
        8526.706415808387,
        8465.281394915513,
        8402.068531439729,
        8465.97800630097,
        8511.390836372173,
        8367.330071060862,
        8458.408205674272,
        8599.521092416799,
        8307.103131045167,
        8481.229777273496,
        8563.128809806864,
        8423.883209864383
    ],
    "SD0DelayMean": [
        15807.162439759742,
        15448.71916530678,
        15414.744511674937,
        15713.416975590564,
        15481.840175628598,
        15360.660819364573,
        15363.50503799325,
        15420.081130101189,
        15574.809859218769,
        15356.015433918674,
        15317.081842956908,
        15559.549999341334,
        15492.77679429066,
        15480.100067495623,
        15542.441356262028,
        15412.423139827333,
        15634.113966158604,
        15440.52716757516,
        15354.046137782288,
        15607.030432703916,
        15552.732304073119,
        15364.414047112263,
        15503.798152889385,
        15304.928589749887,
        15585.951227988204,
        15611.420666673293,
        15636.31218874189,
        15535.867361784545,
        15395.416484397494,
        15352.799506252824,
        15474.405932939866,
        15396.319389916196,
        15498.82015281726,
        15433.021827077779,
        15071.688711809287,
        15453.051489126694,
        15424.626770112714,
        15550.62942749294,
        15711.955593012839,
        15542.139645929503,
        15650.829590930454,
        15473.317851642623,
        15530.929110545623,
        15318.318096053326,
        15307.67949358654,
        15690.468855098015,
        15483.52344536383,
        15528.103970822418,
        15561.337409814176,
        15307.890803293052
    ],
    "SD0successProbStd": [
        0.0,
        0.0,
        0.0,
        0.0,
        0.0,
        0.0,
        0.0,
        0.0,
        0.0,
        0.0,
        0.0,
        0.0,
        0.0,
        0.0,
        0.0,
        0.0,
        0.0,
        0.0,
        0.0,
        0.0,
        0.0,
        0.0,
        0.0,
        0.0,
        0.0,
        0.0,
        0.0,
        0.0,
        0.0,
        0.0,
        0.0,
        0.0,
        0.0,
        0.0,
        0.0,
        0.0,
        0.0,
        0.0,
        0.0,
        0.0,
        0.0,
        0.0,
        0.0,
        0.0,
        0.0,
        0.0,
        0.0,
        0.0,
        0.0,
        0.0
    ],
    "SD0successProbMean": [
        1.0,
        1.0,
        1.0,
        1.0,
        1.0,
        1.0,
        1.0,
        1.0,
        1.0,
        1.0,
        1.0,
        1.0,
        1.0,
        1.0,
        1.0,
        1.0,
        1.0,
        1.0,
        1.0,
        1.0,
        1.0,
        1.0,
        1.0,
        1.0,
        1.0,
        1.0,
        1.0,
        1.0,
        1.0,
        1.0,
        1.0,
        1.0,
        1.0,
        1.0,
        1.0,
        1.0,
        1.0,
        1.0,
        1.0,
        1.0,
        1.0,
        1.0,
        1.0,
        1.0,
        1.0,
        1.0,
        1.0,
        1.0,
        1.0,
        1.0
    ],
    "SD0nonMarkingProbStd": [
        0.0,
        0.0,
        0.0,
        0.0,
        0.0,
        0.0,
        0.0,
        0.0,
        0.0,
        0.0,
        0.0,
        0.0,
        0.0,
        0.0,
        0.0,
        0.0,
        0.0,
        0.0,
        0.0,
        0.0,
        0.0,
        0.0,
        0.0,
        0.0,
        0.0,
        0.0,
        0.01272466496398219,
        0.0,
        0.0,
        0.0,
        0.0,
        0.0,
        0.0,
        0.0,
        0.0,
        0.0,
        0.0,
        0.0,
        0.0,
        0.0,
        0.0,
        0.0,
        0.0,
        0.0,
        0.0,
        0.0,
        0.0,
        0.0,
        0.0,
        0.0
    ],
    "SD0nonMarkingProbMean": [
        1.0,
        1.0,
        1.0,
        1.0,
        1.0,
        1.0,
        1.0,
        1.0,
        1.0,
        1.0,
        1.0,
        1.0,
        1.0,
        1.0,
        1.0,
        1.0,
        1.0,
        1.0,
        1.0,
        1.0,
        1.0,
        1.0,
        1.0,
        1.0,
        1.0,
        1.0,
        0.9998380829015544,
        1.0,
        1.0,
        1.0,
        1.0,
        1.0,
        1.0,
        1.0,
        1.0,
        1.0,
        1.0,
        1.0,
        1.0,
        1.0,
        1.0,
        1.0,
        1.0,
        1.0,
        1.0,
        1.0,
        1.0,
        1.0,
        1.0,
        1.0
    ],
    "SD0lastNonMarkingProbStd": [
        0.0,
        0.0,
        0.0,
        0.0,
        0.0,
        0.0,
        0.0,
        0.012913173184291707,
        0.0,
        0.0,
        0.012824729401064425,
        0.0,
        0.0,
        0.0,
        0.01278274981412284,
        0.012857549581980997,
        0.0,
        0.0,
        0.0,
        0.0,
        0.0,
        0.0,
        0.0,
        0.0,
        0.012794253088668606,
        0.0,
        0.01272466496398219,
        0.0,
        0.0,
        0.0,
        0.0,
        0.0,
        0.0,
        0.0182833378413474,
        0.0,
        0.0128405787122424,
        0.0,
        0.01297716729491983,
        0.0,
        0.0,
        0.012971707132564722,
        0.0,
        0.0,
        0.0,
        0.012906718211039439,
        0.0,
        0.0,
        0.0,
        0.0,
        0.013016685067210315
    ],
    "SD0lastNonMarkingProbMean": [
        1.0,
        1.0,
        1.0,
        1.0,
        1.0,
        1.0,
        1.0,
        0.9998332499583125,
        1.0,
        1.0,
        0.9998355263157894,
        1.0,
        1.0,
        1.0,
        0.9998366013071895,
        0.9998346834187469,
        1.0,
        1.0,
        1.0,
        1.0,
        1.0,
        1.0,
        1.0,
        1.0,
        0.999836307087903,
        1.0,
        0.9998380829015544,
        1.0,
        1.0,
        1.0,
        1.0,
        1.0,
        1.0,
        0.9996656636576395,
        1.0,
        0.9998351195383347,
        1.0,
        0.9998315931289997,
        1.0,
        1.0,
        0.999831734814067,
        1.0,
        1.0,
        1.0,
        0.9998334166250208,
        1.0,
        1.0,
        1.0,
        1.0,
        0.9998305659098611
    ]
}